kaziro/__init__.py
kaziro/api/__init__.py
kaziro/api/generated/.github/workflows/python.yml
kaziro/api/generated/.gitignore
kaziro/api/generated/.gitlab-ci.yml
kaziro/api/generated/.openapi-generator/FILES
kaziro/api/generated/.openapi-generator/VERSION
kaziro/api/generated/.openapi-generator-ignore
kaziro/api/generated/.travis.yml
kaziro/api/generated/README.md
kaziro/api/generated/docs/AcceptOrdersRequest.md
kaziro/api/generated/docs/AcceptOrdersResponse.md
kaziro/api/generated/docs/AcceptedOrder.md
kaziro/api/generated/docs/BrokerApi.md
kaziro/api/generated/docs/BrokerChatCompletionChoice.md
kaziro/api/generated/docs/BrokerChatCompletionMessage.md
kaziro/api/generated/docs/BrokerChatCompletionResponse.md
kaziro/api/generated/docs/BrokerMessageRequest.md
kaziro/api/generated/docs/BrokerThreadCreateResponse.md
kaziro/api/generated/docs/BrokerThreadMetadata.md
kaziro/api/generated/docs/Chat.md
kaziro/api/generated/docs/ChatApi.md
kaziro/api/generated/docs/ChatCompletionChoice.md
kaziro/api/generated/docs/ChatCompletionMessage.md
kaziro/api/generated/docs/ChatCompletionResponse.md
kaziro/api/generated/docs/ChatCreationRequest.md
kaziro/api/generated/docs/ChatExtended.md
kaziro/api/generated/docs/ChatRetrievalResponse.md
kaziro/api/generated/docs/ChatWithMarketAndOrder.md
kaziro/api/generated/docs/DefaultReplyOrder.md
kaziro/api/generated/docs/ErrorResponse.md
kaziro/api/generated/docs/ErrorResponseDetail.md
kaziro/api/generated/docs/HTTPValidationError.md
kaziro/api/generated/docs/Market.md
kaziro/api/generated/docs/MarketApi.md
kaziro/api/generated/docs/MarketCreationResponse.md
kaziro/api/generated/docs/MarketCreationResponseMarketsInner.md
kaziro/api/generated/docs/MarketDetail.md
kaziro/api/generated/docs/MarketOHLCData.md
kaziro/api/generated/docs/MarketPriceHistoryResponse.md
kaziro/api/generated/docs/MarketRetrievalResponse.md
kaziro/api/generated/docs/MessageRequest.md
kaziro/api/generated/docs/OHLCData.md
kaziro/api/generated/docs/OpenOrdersResponse.md
kaziro-1.0.6.dist-info/LICENSE
kaziro-1.0.6.dist-info/METADATA
kaziro-1.0.6.dist-info/WHEEL
kaziro-1.0.6.dist-info/RECORD
