Metadata-Version: 2.1
Name: kaziro
Version: 1.0.6
Summary: Kaziro API Client
Home-page: https://github.com/kazirocom/package
License: LICENSE
Keywords: OpenAPI,OpenAPI-Generator,FastAPI,Kaziro
Author: Kaziro Engineering Team
Author-email: engineering@kaziro.xyz
Requires-Python: >=3.8,<4.0
Classifier: License :: Other/Proprietary License
Classifier: Programming Language :: Python :: 3
Classifier: Programming Language :: Python :: 3.8
Classifier: Programming Language :: Python :: 3.9
Classifier: Programming Language :: Python :: 3.10
Classifier: Programming Language :: Python :: 3.11
Classifier: Programming Language :: Python :: 3.12
Classifier: Programming Language :: Python :: 3.13
Requires-Dist: pydantic (>=2)
Requires-Dist: python-dateutil (>=2.8.2)
Requires-Dist: requests (>=2.25.1,<3.0.0)
Requires-Dist: typing-extensions (>=4.7.1)
Requires-Dist: urllib3 (>=1.25.3,<3.0.0)
Requires-Dist: websocket-client (>=1.2.1,<2.0.0)
Project-URL: Repository, https://github.com/kazirocom/package
